{
  "id": "ada9c606-3d46-45ff-bb45-0cc34b83c105",
  "prevId": "c6901c47-8bcf-4dc7-98e1-731247636238",
  "version": "7",
  "dialect": "postgresql",
  "tables": {
    "public.alerts": {
      "name": "alerts",
      "schema": "",
      "columns": {
        "id": {
          "name": "id",
          "type": "uuid",
          "primaryKey": true,
          "notNull": true,
          "default": "gen_random_uuid()"
        },
        "dependency_id": {
          "name": "dependency_id",
          "type": "uuid",
          "primaryKey": false,
          "notNull": true
        },
        "diff_id": {
          "name": "diff_id",
          "type": "uuid",
          "primaryKey": false,
          "notNull": true
        },
        "channel": {
          "name": "channel",
          "type": "text",
          "primaryKey": false,
          "notNull": true
        },
        "status": {
          "name": "status",
          "type": "text",
          "primaryKey": false,
          "notNull": true
        },
        "error": {
          "name": "error",
          "type": "text",
          "primaryKey": false,
          "notNull": false
        },
        "created_at": {
          "name": "created_at",
          "type": "timestamp with time zone",
          "primaryKey": false,
          "notNull": true,
          "default": "now()"
        }
      },
      "indexes": {},
      "foreignKeys": {
        "alerts_dependency_id_dependencies_id_fk": {
          "name": "alerts_dependency_id_dependencies_id_fk",
          "tableFrom": "alerts",
          "tableTo": "dependencies",
          "columnsFrom": ["dependency_id"],
          "columnsTo": ["id"],
          "onDelete": "cascade",
          "onUpdate": "no action"
        },
        "alerts_diff_id_diffs_id_fk": {
          "name": "alerts_diff_id_diffs_id_fk",
          "tableFrom": "alerts",
          "tableTo": "diffs",
          "columnsFrom": ["diff_id"],
          "columnsTo": ["id"],
          "onDelete": "cascade",
          "onUpdate": "no action"
        }
      },
      "compositePrimaryKeys": {},
      "uniqueConstraints": {},
      "policies": {},
      "checkConstraints": {},
      "isRLSEnabled": false
    },
    "public.baselines": {
      "name": "baselines",
      "schema": "",
      "columns": {
        "id": {
          "name": "id",
          "type": "uuid",
          "primaryKey": true,
          "notNull": true,
          "default": "gen_random_uuid()"
        },
        "dependency_id": {
          "name": "dependency_id",
          "type": "uuid",
          "primaryKey": false,
          "notNull": true
        },
        "schema": {
          "name": "schema",
          "type": "jsonb",
          "primaryKey": false,
          "notNull": true
        },
        "sample_count": {
          "name": "sample_count",
          "type": "integer",
          "primaryKey": false,
          "notNull": true
        },
        "status": {
          "name": "status",
          "type": "text",
          "primaryKey": false,
          "notNull": true,
          "default": "'active'"
        },
        "locked_at": {
          "name": "locked_at",
          "type": "timestamp with time zone",
          "primaryKey": false,
          "notNull": true,
          "default": "now()"
        }
      },
      "indexes": {},
      "foreignKeys": {
        "baselines_dependency_id_dependencies_id_fk": {
          "name": "baselines_dependency_id_dependencies_id_fk",
          "tableFrom": "baselines",
          "tableTo": "dependencies",
          "columnsFrom": ["dependency_id"],
          "columnsTo": ["id"],
          "onDelete": "cascade",
          "onUpdate": "no action"
        }
      },
      "compositePrimaryKeys": {},
      "uniqueConstraints": {},
      "policies": {},
      "checkConstraints": {},
      "isRLSEnabled": false
    },
    "public.dependencies": {
      "name": "dependencies",
      "schema": "",
      "columns": {
        "id": {
          "name": "id",
          "type": "uuid",
          "primaryKey": true,
          "notNull": true,
          "default": "gen_random_uuid()"
        },
        "name": {
          "name": "name",
          "type": "text",
          "primaryKey": false,
          "notNull": true
        },
        "kind": {
          "name": "kind",
          "type": "text",
          "primaryKey": false,
          "notNull": true,
          "default": "'rest'"
        },
        "capture_mode": {
          "name": "capture_mode",
          "type": "text",
          "primaryKey": false,
          "notNull": true,
          "default": "'poll'"
        },
        "url": {
          "name": "url",
          "type": "text",
          "primaryKey": false,
          "notNull": true
        },
        "method": {
          "name": "method",
          "type": "text",
          "primaryKey": false,
          "notNull": true,
          "default": "'GET'"
        },
        "headers": {
          "name": "headers",
          "type": "jsonb",
          "primaryKey": false,
          "notNull": true,
          "default": "'{}'::jsonb"
        },
        "poll_interval_seconds": {
          "name": "poll_interval_seconds",
          "type": "integer",
          "primaryKey": false,
          "notNull": true,
          "default": 300
        },
        "baseline_window": {
          "name": "baseline_window",
          "type": "integer",
          "primaryKey": false,
          "notNull": true,
          "default": 5
        },
        "contract_schema": {
          "name": "contract_schema",
          "type": "jsonb",
          "primaryKey": false,
          "notNull": false
        },
        "alert_threshold": {
          "name": "alert_threshold",
          "type": "text",
          "primaryKey": false,
          "notNull": true,
          "default": "'WARNING'"
        },
        "enabled": {
          "name": "enabled",
          "type": "boolean",
          "primaryKey": false,
          "notNull": true,
          "default": true
        },
        "created_at": {
          "name": "created_at",
          "type": "timestamp with time zone",
          "primaryKey": false,
          "notNull": true,
          "default": "now()"
        }
      },
      "indexes": {},
      "foreignKeys": {},
      "compositePrimaryKeys": {},
      "uniqueConstraints": {},
      "policies": {},
      "checkConstraints": {},
      "isRLSEnabled": false
    },
    "public.diffs": {
      "name": "diffs",
      "schema": "",
      "columns": {
        "id": {
          "name": "id",
          "type": "uuid",
          "primaryKey": true,
          "notNull": true,
          "default": "gen_random_uuid()"
        },
        "dependency_id": {
          "name": "dependency_id",
          "type": "uuid",
          "primaryKey": false,
          "notNull": true
        },
        "baseline_id": {
          "name": "baseline_id",
          "type": "uuid",
          "primaryKey": false,
          "notNull": true
        },
        "entries": {
          "name": "entries",
          "type": "jsonb",
          "primaryKey": false,
          "notNull": true
        },
        "severity": {
          "name": "severity",
          "type": "text",
          "primaryKey": false,
          "notNull": true
        },
        "captured_schema": {
          "name": "captured_schema",
          "type": "jsonb",
          "primaryKey": false,
          "notNull": true
        },
        "created_at": {
          "name": "created_at",
          "type": "timestamp with time zone",
          "primaryKey": false,
          "notNull": true,
          "default": "now()"
        },
        "last_seen_at": {
          "name": "last_seen_at",
          "type": "timestamp with time zone",
          "primaryKey": false,
          "notNull": true,
          "default": "now()"
        },
        "resolved_at": {
          "name": "resolved_at",
          "type": "timestamp with time zone",
          "primaryKey": false,
          "notNull": false
        }
      },
      "indexes": {},
      "foreignKeys": {
        "diffs_dependency_id_dependencies_id_fk": {
          "name": "diffs_dependency_id_dependencies_id_fk",
          "tableFrom": "diffs",
          "tableTo": "dependencies",
          "columnsFrom": ["dependency_id"],
          "columnsTo": ["id"],
          "onDelete": "cascade",
          "onUpdate": "no action"
        },
        "diffs_baseline_id_baselines_id_fk": {
          "name": "diffs_baseline_id_baselines_id_fk",
          "tableFrom": "diffs",
          "tableTo": "baselines",
          "columnsFrom": ["baseline_id"],
          "columnsTo": ["id"],
          "onDelete": "cascade",
          "onUpdate": "no action"
        }
      },
      "compositePrimaryKeys": {},
      "uniqueConstraints": {},
      "policies": {},
      "checkConstraints": {},
      "isRLSEnabled": false
    },
    "public.samples": {
      "name": "samples",
      "schema": "",
      "columns": {
        "id": {
          "name": "id",
          "type": "uuid",
          "primaryKey": true,
          "notNull": true,
          "default": "gen_random_uuid()"
        },
        "dependency_id": {
          "name": "dependency_id",
          "type": "uuid",
          "primaryKey": false,
          "notNull": true
        },
        "body": {
          "name": "body",
          "type": "jsonb",
          "primaryKey": false,
          "notNull": true
        },
        "captured_at": {
          "name": "captured_at",
          "type": "timestamp with time zone",
          "primaryKey": false,
          "notNull": true,
          "default": "now()"
        }
      },
      "indexes": {},
      "foreignKeys": {
        "samples_dependency_id_dependencies_id_fk": {
          "name": "samples_dependency_id_dependencies_id_fk",
          "tableFrom": "samples",
          "tableTo": "dependencies",
          "columnsFrom": ["dependency_id"],
          "columnsTo": ["id"],
          "onDelete": "cascade",
          "onUpdate": "no action"
        }
      },
      "compositePrimaryKeys": {},
      "uniqueConstraints": {},
      "policies": {},
      "checkConstraints": {},
      "isRLSEnabled": false
    }
  },
  "enums": {},
  "schemas": {},
  "sequences": {},
  "roles": {},
  "policies": {},
  "views": {},
  "_meta": {
    "columns": {},
    "schemas": {},
    "tables": {}
  }
}
